[
  {
    "type": "function",
    "name": "createListing",
    "inputs": [
      {
        "name": "itemId",
        "type": "uint256",
        "internalType": "uint256"
      },
      {
        "name": "amount",
        "type": "uint256",
        "internalType": "uint256"
      },
      {
        "name": "pricePerItem",
        "type": "uint256",
        "internalType": "uint256"
      }
    ],
    "outputs": [
      {
        "name": "",
        "type": "uint256",
        "internalType": "uint256"
      }
    ],
    "stateMutability": "nonpayable"
  },
  {
    "type": "function",
    "name": "buyItem",
    "inputs": [
      {
        "name": "listingId",
        "type": "uint256",
        "internalType": "uint256"
      },
      {
        "name": "amount",
        "type": "uint256",
        "internalType": "uint256"
      }
    ],
    "outputs": [],
    "stateMutability": "payable"
  },
  {
    "type": "function",
    "name": "getListing",
    "inputs": [
      {
        "name": "listingId",
        "type": "uint256",
        "internalType": "uint256"
      }
    ],
    "outputs": [
      {
        "name": "",
        "type": "tuple",
        "internalType": "struct IRuneraMarketplace.Listing",
        "components": [
          {
            "name": "listingId",
            "type": "uint256",
            "internalType": "uint256"
          },
          {
            "name": "seller",
            "type": "address",
            "internalType": "address"
          },
          {
            "name": "itemId",
            "type": "uint256",
            "internalType": "uint256"
          },
          {
            "name": "amount",
            "type": "uint256",
            "internalType": "uint256"
          },
          {
            "name": "pricePerItem",
            "type": "uint256",
            "internalType": "uint256"
          },
          {
            "name": "isActive",
            "type": "bool",
            "internalType": "bool"
          }
        ]
      }
    ],
    "stateMutability": "view"
  },
  {
    "type": "function",
    "name": "cancelListing",
    "inputs": [
      {
        "name": "listingId",
        "type": "uint256",
        "internalType": "uint256"
      }
    ],
    "outputs": [],
    "stateMutability": "nonpayable"
  }
]
